quickest/__init__.py
quickest/cost.py
quickest/dynamics.py
quickest/filter.py
quickest/optim.py
quickest/policy.py
quickest/process.py
quickest/sensor.py
quickest/types.py
quickest/util.py
quickest-0.1.1.dist-info/WHEEL
quickest-0.1.1.dist-info/METADATA
quickest-0.1.1.dist-info/RECORD
